pgparse.py
xmpdf.py
xmpdf-0.7.0.dist-info/LICENSE
xmpdf-0.7.0.dist-info/METADATA
xmpdf-0.7.0.dist-info/WHEEL
xmpdf-0.7.0.dist-info/top_level.txt
xmpdf-0.7.0.dist-info/RECORD
