Metadata-Version: 2.1
Name: xmpdf
Version: 0.7.0
Summary: Extracts email metadata and text from a PDF file
Home-page: https://github.com/history-lab/xmpdf
Author: Ben Lis, History Lab @ Columbia University
License: MIT License
Platform: UNKNOWN
Requires-Python: >=3.8
License-File: LICENSE
Requires-Dist: pdftotext
Requires-Dist: jsonpickle
